api_tools/__init__.py
api_tools/models.py
api_tools/scripts.py
api_tools/settings.py
api_tools/urls.py
api_tools/utils.py
django_api_toolkit-0.0.2.dist-info/DESCRIPTION.rst
django_api_toolkit-0.0.2.dist-info/METADATA
django_api_toolkit-0.0.2.dist-info/RECORD
django_api_toolkit-0.0.2.dist-info/WHEEL
django_api_toolkit-0.0.2.dist-info/entry_points.txt
django_api_toolkit-0.0.2.dist-info/metadata.json
django_api_toolkit-0.0.2.dist-info/top_level.txt
